[
 {
  "handle": "_TpSju",
  "name": "봉이모바일 상무점",
  "region": "광주광역시 서구",
  "hq": "서부",
  "url": "https://pf.kakao.com/_TpSju/107352347",
  "type": "kakao"
 },
 {
  "handle": "_jzRhn",
  "name": "봉이모바일 익산점",
  "region": "전라북도 익산시",
  "hq": "서부",
  "url": "https://pf.kakao.com/_jzRhn/107347520",
  "type": "kakao"
 },
 {
  "handle": "_fSqxlT",
  "name": "봉이모바일 전남대점",
  "region": "광주광역시 북구",
  "hq": "서부",
  "url": "https://pf.kakao.com/_fSqxlT/107330381",
  "type": "kakao"
 },
 {
  "handle": "_Upxkwxj",
  "name": "봉이모바일 신창점(송이)",
  "region": "광주광역시 광산구",
  "hq": "서부",
  "url": "https://pf.kakao.com/_Upxkwxj/107348045",
  "type": "kakao"
 },
 {
  "handle": "_xhpxkwxj",
  "name": "봉이모바일 목포남악점",
  "region": "전라남도 무안군",
  "hq": "서부",
  "url": "https://pf.kakao.com/_xhpxkwxj/107348873",
  "type": "kakao"
 },
 {
  "handle": "_xhYxkwxj",
  "name": "봉이모바일 첨단점",
  "region": "광주광역시 북구",
  "hq": "서부",
  "url": "https://pf.kakao.com/_xhYxkwxj/107348428",
  "type": "kakao"
 },
 {
  "handle": "_MnxkxhX",
  "name": "봉이모바일 여수점",
  "region": "전라남도 여수시",
  "hq": "서부",
  "url": "https://pf.kakao.com/_MnxkxhX/112906046",
  "type": "kakao"
 },
 {
  "handle": "_xnArxon",
  "name": "휴대폰성지 따르릉통신 철산역점",
  "region": "경기도 광명시",
  "hq": "수도권",
  "url": "https://pf.kakao.com/_xnArxon/112144690",
  "type": "kakao"
 },
 {
  "handle": "_bHman",
  "name": "따르릉통신 둔촌동역점",
  "region": "서울특별시 강동구",
  "hq": "수도권",
  "url": "https://pf.kakao.com/_bHman/110152112",
  "type": "kakao"
 },
 {
  "handle": "_TxaZSn",
  "name": "휴대폰성지 따르릉 둔촌점",
  "region": "서울특별시 강동구",
  "hq": "수도권",
  "url": "https://pf.kakao.com/_TxaZSn/posts",
  "type": "kakao"
 },
 {
  "handle": "_Yxkxehxb",
  "name": "휴대폰성지 따르릉통신 부산대점",
  "region": "부산광역시 금정구",
  "hq": "부산",
  "url": "https://pf.kakao.com/_Yxkxehxb/107358112",
  "type": "kakao"
 },
 {
  "handle": "_MxbwNn",
  "name": "휴대폰성지 따르릉통신 사직점",
  "region": "부산광역시 동래구",
  "hq": "부산",
  "url": "https://pf.kakao.com/_MxbwNn/110396096",
  "type": "kakao"
 },
 {
  "handle": "_QGxdPs",
  "name": "굳폰 성동구 휴대폰 성지",
  "region": "서울특별시 성동구",
  "hq": "수도권",
  "url": "https://pf.kakao.com/_QGxdPs/104744611",
  "type": "kakao"
 },
 {
  "handle": "_jJEcG",
  "name": "굳폰 DMC 디엠씨 휴대폰 성지",
  "region": "서울특별시 은평구",
  "hq": "수도권",
  "url": "https://pf.kakao.com/_jJEcG/105529531",
  "type": "kakao"
 },
 {
  "handle": "_HTUPn",
  "name": "굳폰 창동휴대폰성지",
  "region": "서울특별시 도봉구",
  "hq": "수도권",
  "url": "https://pf.kakao.com/_HTUPn/109132745",
  "type": "kakao"
 },
 {
  "handle": "_iBRzb",
  "name": "가산 휴대폰 성지",
  "region": "서울특별시 금천구",
  "hq": "수도권",
  "url": "https://pf.kakao.com/_iBRzb/99987274",
  "type": "kakao"
 },
 {
  "handle": "_LInEn",
  "name": "굳폰 다산휴대폰성지",
  "region": "경기도 남양주시",
  "hq": "수도권",
  "url": "https://pf.kakao.com/_LInEn/107300038",
  "type": "kakao"
 },
 {
  "handle": "_qJxfjn",
  "name": "굳폰 아산성지",
  "region": "충청남도 아산시",
  "hq": "중부",
  "url": "https://pf.kakao.com/_qJxfjn/110173570",
  "type": "kakao"
 },
 {
  "handle": "_NJvin",
  "name": "굳폰 청주성지",
  "region": "충청북도 청주시",
  "hq": "중부",
  "url": "https://pf.kakao.com/_NJvin/110173606",
  "type": "kakao"
 },
 {
  "handle": "_xdbGxkG",
  "name": "굳폰 세종성지",
  "region": "세종특별자치시",
  "hq": "중부",
  "url": "https://pf.kakao.com/_xdbGxkG/110173455",
  "type": "kakao"
 },
 {
  "handle": "_xkFxdqX",
  "name": "휴대폰성지 일타폰 목동점",
  "region": "서울특별시 양천구",
  "hq": "수도권",
  "url": "https://pf.kakao.com/_xkFxdqX/112553474",
  "type": "kakao"
 },
 {
  "handle": "_luMtT",
  "name": "휴대폰성지 일타폰 마곡점",
  "region": "서욱특별시 강서구",
  "hq": "수도권",
  "url": "https://pf.kakao.com/_luMtT/104060033",
  "type": "kakao"
 },
 {
  "handle": "_nxlMtT",
  "name": "휴대폰성지 일타폰 파주점",
  "region": "경기도 파주시",
  "hq": "수도권",
  "url": "https://pf.kakao.com/_nxlMtT/107800364",
  "type": "kakao"
 },
 {
  "handle": "_BxbxjPxj",
  "name": "휴대폰성지 일타폰 이수역점",
  "region": "서울특별시 동작구",
  "hq": "수도권",
  "url": "https://pf.kakao.com/_BxbxjPxj/109503761",
  "type": "kakao"
 },
 {
  "handle": "_xokxmxjG",
  "name": "휴대폰성지 일타폰 판교점",
  "region": "경기도 성남시",
  "hq": "수도권",
  "url": "https://pf.kakao.com/_xokxmxjG/104060025",
  "type": "kakao"
 },
 {
  "handle": "_vxnGRG",
  "name": "휴대폰성지 일타폰 청라점",
  "region": "인천광역시 서구",
  "hq": "수도권",
  "url": "https://pf.kakao.com/_vxnGRG/109333854",
  "type": "kakao"
 },
 {
  "handle": "_mIMtT",
  "name": "휴대폰성지 일타폰 동대문점",
  "region": "서욱특별시 종로구",
  "hq": "수도권",
  "url": "https://pf.kakao.com/_mIMtT/104840334",
  "type": "kakao"
 },
 {
  "handle": "_bISxoG",
  "name": "휴대폰성지 직폰 위례점",
  "region": "서울특별시 송파구",
  "hq": "수도권",
  "url": "https://pf.kakao.com/_bISxoG/110604149",
  "type": "kakao"
 },
 {
  "handle": "_XZcxkn",
  "name": "직폰 월계점",
  "region": "서울특별시 노원구",
  "hq": "수도권",
  "url": "https://pf.kakao.com/_XZcxkn/111471762",
  "type": "kakao"
 },
 {
  "handle": "_hFsXn",
  "name": "휴대폰성지-직폰-가산점(금천구)",
  "region": "서울특별시 금천구",
  "hq": "수도권",
  "url": "https://pf.kakao.com/_hFsXn/109167050",
  "type": "kakao"
 },
 {
  "handle": "_iDaqn",
  "name": "휴대폰성지 직폰 동탄점",
  "region": "경기도 화성시",
  "hq": "수도권",
  "url": "https://pf.kakao.com/_iDaqn/111331340",
  "type": "kakao"
 },
 {
  "handle": "_xawBmn",
  "name": "휴대폰성지 직폰 평택점",
  "region": "경기도 평택시",
  "hq": "수도권",
  "url": "https://pf.kakao.com/_xawBmn/110334582",
  "type": "kakao"
 },
 {
  "handle": "_pbyxmn",
  "name": "휴대폰성지 직폰 의정부점",
  "region": "경기도 의정부시",
  "hq": "수도권",
  "url": "https://pf.kakao.com/_pbyxmn/111333621",
  "type": "kakao"
 },
 {
  "handle": "_xgxjsWG",
  "name": "휴대폰성지 직폰 시흥점",
  "region": "경기도 시흥시",
  "hq": "수도권",
  "url": "https://pf.kakao.com/_xgxjsWG/111331603",
  "type": "kakao"
 },
 {
  "handle": "_xfnxgHn",
  "name": "휴대폰성지 직폰 인계점",
  "region": "경기도 수원시",
  "hq": "수도권",
  "url": "https://pf.kakao.com/_xfnxgHn/111471827",
  "type": "kakao"
 },
 {
  "handle": "_JZexlG",
  "name": "휴대폰성지 직폰 분당점",
  "region": "경기도 성남시",
  "hq": "수도권",
  "url": "https://pf.kakao.com/_JZexlG/108952078",
  "type": "kakao"
 },
 {
  "handle": "_lxmfxfn",
  "name": "휴대폰성지 직폰 남양주점",
  "region": "경기도 남양주시",
  "hq": "수도권",
  "url": "https://pf.kakao.com/_lxmfxfn/109876956",
  "type": "kakao"
 },
 {
  "handle": "_xgIexlG",
  "name": "휴대폰성지 직폰 김포점",
  "region": "경기도 김포시",
  "hq": "수도권",
  "url": "https://pf.kakao.com/_xgIexlG/111331331",
  "type": "kakao"
 },
 {
  "handle": "_Arxhxcn",
  "name": "울산 휴대폰성지 직폰 병영점",
  "region": "울산시 중구",
  "hq": "부산",
  "url": "https://pf.kakao.com/_Arxhxcn/111202779",
  "type": "kakao"
 },
 {
  "handle": "_WrvFn",
  "name": "울산 휴대폰성지 직폰 덕하점",
  "region": "울산시 을주군",
  "hq": "부산",
  "url": "https://pf.kakao.com/_WrvFn/109990912",
  "type": "kakao"
 },
 {
  "handle": "_exdhxen",
  "name": "울산 휴대폰성지 직폰 송정점",
  "region": "울산시 북구",
  "hq": "부산",
  "url": "https://pf.kakao.com/_exdhxen/110632314",
  "type": "kakao"
 },
 {
  "handle": "_FzTRX",
  "name": "울산 휴대폰성지 직폰 강동점",
  "region": "울산시 북구",
  "hq": "부산",
  "url": "https://pf.kakao.com/_FzTRX/112356336",
  "type": "kakao"
 },
 {
  "handle": "_Pqdxnn",
  "name": "울산 휴대폰성지 직폰 무거점",
  "region": "울산시 남구",
  "hq": "부산",
  "url": "https://pf.kakao.com/_Pqdxnn/112658475",
  "type": "kakao"
 },
 {
  "handle": "_pWqzX",
  "name": "울산 휴대폰성지 직폰 삼산점",
  "region": "울산시 남구",
  "hq": "부산",
  "url": "https://pf.kakao.com/_pWqzX/112468842",
  "type": "kakao"
 },
 {
  "handle": "_PGxkWG",
  "name": "휴대폰성지 직폰 - 부산 경남 울산",
  "region": "부산광역시/울산/경남",
  "hq": "부산",
  "url": "https://pf.kakao.com/_PGxkWG/108703601",
  "type": "kakao"
 },
 {
  "handle": "_mUvHn",
  "name": "부산 휴대폰성지 직폰 센텀점",
  "region": "부산광역시 해운대구",
  "hq": "부산",
  "url": "https://pf.kakao.com/_mUvHn/112992609",
  "type": "kakao"
 },
 {
  "handle": "_mXatG",
  "name": "휴대폰성지 직폰 시청점",
  "region": "부산광역시 연제구",
  "hq": "부산",
  "url": "https://pf.kakao.com/_mXatG/109806613",
  "type": "kakao"
 },
 {
  "handle": "_ZVTRX",
  "name": "부산 휴대폰성지 직폰 사직점",
  "region": "부산광역시 연제구",
  "hq": "부산",
  "url": "https://pf.kakao.com/_ZVTRX/112463538",
  "type": "kakao"
 },
 {
  "handle": "_xjxaEgn",
  "name": "부산 휴대폰성지 직폰 남천점",
  "region": "부산광역시 수영구",
  "hq": "부산",
  "url": "https://pf.kakao.com/_xjxaEgn/112974784",
  "type": "kakao"
 },
 {
  "handle": "_EKYCn",
  "name": "부산 휴대폰성지 직폰 북구덕천점",
  "region": "부산광역시 북구",
  "hq": "부산",
  "url": "https://pf.kakao.com/_EKYCn/108768306",
  "type": "kakao"
 },
 {
  "handle": "_ulsun",
  "name": "부산 휴대폰성지 직폰 서면점",
  "region": "부산광역시 부산진구",
  "hq": "부산",
  "url": "https://pf.kakao.com/_ulsun/109142926",
  "type": "kakao"
 },
 {
  "handle": "_JsstG",
  "name": "부산 휴대폰성지 직폰 정관점",
  "region": "부산광역시 기장군",
  "hq": "부산",
  "url": "https://pf.kakao.com/_JsstG/106402087",
  "type": "kakao"
 },
 {
  "handle": "_xcxafun",
  "name": "부산 휴대폰성지 직폰 구서점",
  "region": "부산광역시 금정구",
  "hq": "부산",
  "url": "https://pf.kakao.com/_xcxafun/110276733",
  "type": "kakao"
 },
 {
  "handle": "_lrCaG",
  "name": "창원 휴대폰성지 직폰 장천점",
  "region": "경상남도 창원시",
  "hq": "부산",
  "url": "https://pf.kakao.com/_lrCaG/109063373",
  "type": "kakao"
 },
 {
  "handle": "_ALDCn",
  "name": "창원 휴대폰성지 직폰 용원점",
  "region": "경상남도 창원시",
  "hq": "부산",
  "url": "https://pf.kakao.com/_ALDCn/109298881",
  "type": "kakao"
 },
 {
  "handle": "_KQuqX",
  "name": "창원 휴대폰성지 직폰 석동점",
  "region": "경상남도 창원시",
  "hq": "부산",
  "url": "https://pf.kakao.com/_KQuqX/112568419",
  "type": "kakao"
 },
 {
  "handle": "_ZFxmeb",
  "name": "김해 휴대폰성지 직폰 진영점",
  "region": "경상남도 김해시",
  "hq": "부산",
  "url": "https://pf.kakao.com/_ZFxmeb/108826978",
  "type": "kakao"
 },
 {
  "handle": "_xicxoWG",
  "name": "휴대폰성지 직폰 - 대구 경북",
  "region": "대구광역시/경북",
  "hq": "대구",
  "url": "https://pf.kakao.com/_xicxoWG/108703579",
  "type": "kakao"
 },
 {
  "handle": "_teyxjn",
  "name": "대구 휴대폰성지 직폰 동성로점",
  "region": "대구광역시 중구",
  "hq": "대구",
  "url": "https://pf.kakao.com/_teyxjn/108872219",
  "type": "kakao"
 },
 {
  "handle": "_xnyMcn",
  "name": "직폰 대구성서점",
  "region": "대구광역시 달서구",
  "hq": "대구",
  "url": "https://pf.kakao.com/_xnyMcn/111750730",
  "type": "kakao"
 },
 {
  "handle": "_xcGBFn",
  "name": "휴대폰성지 직폰 대명점",
  "region": "대구광역시 남구",
  "hq": "대구",
  "url": "https://pf.kakao.com/_xcGBFn/110235813",
  "type": "kakao"
 },
 {
  "handle": "_qaaen",
  "name": "포항직폰양덕점",
  "region": "경상북도 포항",
  "hq": "대구",
  "url": "https://pf.kakao.com/_qaaen/111000927",
  "type": "kakao"
 },
 {
  "handle": "_VExkYn",
  "name": "휴대폰성지 직폰 산동점",
  "region": "경상북도 구미시",
  "hq": "대구",
  "url": "https://pf.kakao.com/_VExkYn/111741697",
  "type": "kakao"
 },
 {
  "handle": "_xbafun",
  "name": "천안 휴대폰성지 직폰 불당점",
  "region": "충청남도 천안시",
  "hq": "중부",
  "url": "https://pf.kakao.com/_xbafun/108587064",
  "type": "kakao"
 },
 {
  "handle": "_rxlebn",
  "name": "천안 휴대폰성지 직폰 청당점",
  "region": "충청남도 천안시",
  "hq": "중부",
  "url": "https://pf.kakao.com/_rxlebn/111392581",
  "type": "kakao"
 },
 {
  "handle": "_xnglUn",
  "name": "천안 휴대폰성지 직폰 성성점",
  "region": "충청남도 천안시",
  "hq": "중부",
  "url": "https://pf.kakao.com/_xnglUn/111089706",
  "type": "kakao"
 },
 {
  "handle": "_NPuzX",
  "name": "아산 휴대폰성지 직폰 배방점",
  "region": "충청남도 아산시",
  "hq": "중부",
  "url": "https://pf.kakao.com/_NPuzX/112554622",
  "type": "kakao"
 },
 {
  "handle": "_xilgqX",
  "name": "아산 휴대폰성지 직폰 아산터미널점",
  "region": "충청남도 아산시",
  "hq": "중부",
  "url": "https://pf.kakao.com/_xilgqX/112727043",
  "type": "kakao"
 },
 {
  "handle": "_xfxkxoWG",
  "name": "휴대폰성지 직폰 대전 세종 충청",
  "region": "대전광역시/세종시/충청",
  "hq": "중부",
  "url": "https://pf.kakao.com/_xfxkxoWG/109002419",
  "type": "kakao"
 },
 {
  "handle": "_xcLxnhG",
  "name": "대전 휴대폰성지 직폰 둔산점",
  "region": "대전광역시 서구",
  "hq": "중부",
  "url": "https://pf.kakao.com/_xcLxnhG/107960214",
  "type": "kakao"
 },
 {
  "handle": "_LxiWyxb",
  "name": "와싸폰 본점",
  "region": "부산광역시 강서구",
  "hq": "부산",
  "url": "https://pf.kakao.com/_LxiWyxb/112934935",
  "type": "kakao"
 },
 {
  "handle": "_LnxmCn",
  "name": "휴대폰성지 와싸폰 국제본점",
  "region": "부산광역시 강서구",
  "hq": "부산",
  "url": "https://pf.kakao.com/_LnxmCn/108741465",
  "type": "kakao"
 },
 {
  "handle": "_DxfxmCn",
  "name": "휴대폰성지 와싸폰 오션점",
  "region": "부산광역시 강서구",
  "hq": "부산",
  "url": "https://pf.kakao.com/_DxfxmCn/109959029",
  "type": "kakao"
 },
 {
  "handle": "_lVDCn",
  "name": "휴대폰성지 와싸폰 국제신도시점",
  "region": "부산광역시 강서구",
  "hq": "부산",
  "url": "https://pf.kakao.com/_lVDCn/108334115",
  "type": "kakao"
 },
 {
  "handle": "_xexljjn",
  "name": "휴대폰성지 와싸폰 남구점",
  "region": "부산광역시 남구",
  "hq": "부산",
  "url": "https://pf.kakao.com/_xexljjn/108844183",
  "type": "kakao"
 },
 {
  "handle": "_xgxnxmCn",
  "name": "휴대폰성지 와싸폰 장산점",
  "region": "부산광역시 해운대구",
  "hq": "부산",
  "url": "https://pf.kakao.com/_xgxnxmCn/108914571",
  "type": "kakao"
 },
 {
  "handle": "_VxcDCn",
  "name": "휴대폰성지 와싸폰 창원 진해점",
  "region": "경상남도 창원시",
  "hq": "부산",
  "url": "https://pf.kakao.com/_VxcDCn/109920261",
  "type": "kakao"
 },
 {
  "handle": null,
  "name": "준텔레콤",
  "region": "유투브 채널",
  "hq": "",
  "url": "https://www.youtube.com/@%EC%A4%80%ED%85%94%EB%A0%88%EC%BD%A4",
  "type": "youtube"
 },
 {
  "handle": null,
  "name": "아정당",
  "region": "유투브 채널",
  "hq": "",
  "url": "https://www.youtube.com/@%EC%95%84%EC%A0%95%EB%8B%B9",
  "type": "youtube"
 },
 {
  "handle": null,
  "name": "KR모바일",
  "region": "유투브 채널",
  "hq": "",
  "url": "https://www.youtube.com/@KR%EB%AA%A8%EB%B0%94%EC%9D%BC",
  "type": "youtube"
 },
 {
  "handle": null,
  "name": "케통령",
  "region": "유투브 채널",
  "hq": "",
  "url": "https://www.youtube.com/@Ktpresident",
  "type": "youtube"
 },
 {
  "handle": null,
  "name": "휴대폰 판매왕(폰킴)",
  "region": "유투브 채널",
  "hq": "",
  "url": "https://www.youtube.com/@Phone_Kim",
  "type": "youtube"
 },
 {
  "handle": null,
  "name": "휴대폰 지식인",
  "region": "유투브 채널",
  "hq": "",
  "url": "https://www.youtube.com/@phone_mania",
  "type": "youtube"
 },
 {
  "handle": null,
  "name": "옆커폰",
  "region": "유투브 채널",
  "hq": "",
  "url": "https://www.youtube.com/@next_town_phone",
  "type": "youtube"
 },
 {
  "handle": null,
  "name": "성지당 SZD",
  "region": "유투브 채널",
  "hq": "",
  "url": "https://www.youtube.com/@%EC%84%B1%EC%A7%80%EB%8B%B9SZD",
  "type": "youtube"
 },
 {
  "handle": null,
  "name": "달인폰센터 고양점",
  "region": "유투브 채널",
  "hq": "",
  "url": "https://www.youtube.com/@%EC%9B%90%ED%9D%A5%EB%8F%84%EB%A7%A4%ED%8F%B0%EC%84%BC%ED%83%80",
  "type": "youtube"
 },
 {
  "handle": null,
  "name": "국대폰",
  "region": "유투브 채널",
  "hq": "",
  "url": "https://www.youtube.com/@no.1gdp",
  "type": "youtube"
 },
 {
  "handle": null,
  "name": "인터넷끝판왕",
  "region": "유투브 채널",
  "hq": "",
  "url": "https://www.youtube.com/@internet_kking",
  "type": "youtube"
 },
 {
  "handle": null,
  "name": "인터넷민족",
  "region": "유투브 채널",
  "hq": "",
  "url": "https://www.youtube.com/@in-min",
  "type": "youtube"
 },
 {
  "handle": null,
  "name": "펭귄통신",
  "region": "유투브 채널",
  "hq": "",
  "url": "https://www.youtube.com/@pgts",
  "type": "youtube"
 },
 {
  "handle": "_NxcPYn",
  "name": "휴대폰 성지 금천점",
  "region": "서울특별시 금천구",
  "hq": "수도권",
  "url": "https://pf.kakao.com/_NxcPYn/posts",
  "type": "kakao"
 },
 {
  "handle": "_hxgHmn",
  "name": "휴대폰 성지 싸당 인천 서구점",
  "region": "인천광역시 서구",
  "hq": "수도권",
  "url": "https://pf.kakao.com/_hxgHmn/112714516",
  "type": "kakao"
 },
 {
  "handle": "_wGXDn",
  "name": "휴대폰 성지 싸당 안산점",
  "region": "경기도 안산시",
  "hq": "수도권",
  "url": "https://pf.kakao.com/_wGXDn/112713977",
  "type": "kakao"
 },
 {
  "handle": "_QaxaTn",
  "name": "휴대폰성지 싸당 은평점",
  "region": "서울특별시 은평구",
  "hq": "수도권",
  "url": "https://pf.kakao.com/_QaxaTn/112714713",
  "type": "kakao"
 },
 {
  "handle": "_UWxaTn",
  "name": "휴대폰성지 싸당 서초점",
  "region": "서울특별시 서초구",
  "hq": "수도권",
  "url": "https://pf.kakao.com/_UWxaTn/112714388",
  "type": "kakao"
 },
 {
  "handle": "_xhmxaTn",
  "name": "휴대폰성지 싸당 부천점",
  "region": "경기도 부천시",
  "hq": "수도권",
  "url": "https://pf.kakao.com/_xhmxaTn/112714361",
  "type": "kakao"
 },
 {
  "handle": "_GrxaTn",
  "name": "휴대폰성지 싸당 의정부점",
  "region": "경기도 의정부시",
  "hq": "수도권",
  "url": "https://pf.kakao.com/_GrxaTn/112706863",
  "type": "kakao"
 },
 {
  "handle": "_GxixaTn",
  "name": "휴대폰성지 싸당 하남점",
  "region": "경기도 하남시",
  "hq": "수도권",
  "url": "https://pf.kakao.com/_GxixaTn/112714562",
  "type": "kakao"
 },
 {
  "handle": "_AWxaTn",
  "name": "휴대폰성지 싸당 용산점",
  "region": "서울특별시 용산구",
  "hq": "수도권",
  "url": "https://pf.kakao.com/_AWxaTn/112714484",
  "type": "kakao"
 },
 {
  "handle": "_IaxaTn",
  "name": "휴대폰성지 싸당 남양주점",
  "region": "경기도 남양주시",
  "hq": "수도권",
  "url": "https://pf.kakao.com/_IaxaTn/112714335",
  "type": "kakao"
 },
 {
  "handle": "_gUexln",
  "name": "휴대폰성지 싸당 중랑점",
  "region": "서울특별시 중랑구",
  "hq": "수도권",
  "url": "https://pf.kakao.com/_gUexln/112714015",
  "type": "kakao"
 },
 {
  "handle": "_uQBdn",
  "name": "휴대폰성지 싸당 노원점",
  "region": "서울특별시 노원구",
  "hq": "수도권",
  "url": "https://pf.kakao.com/_uQBdn/112714256",
  "type": "kakao"
 },
 {
  "handle": "_xcuIbn",
  "name": "휴대폰성지 싸당 고양점",
  "region": "경기도 고양시",
  "hq": "수도권",
  "url": "https://pf.kakao.com/_xcuIbn/112714303",
  "type": "kakao"
 },
 {
  "handle": "_iFxaTn",
  "name": "휴대폰성지 싸당 영등포점",
  "region": "서울특별시 영등포구",
  "hq": "수도권",
  "url": "https://pf.kakao.com/_iFxaTn/112714417",
  "type": "kakao"
 },
 {
  "handle": "_hFxaTn",
  "name": "휴대폰성지 싸당 강서점",
  "region": "서울특별시 강동구",
  "hq": "수도권",
  "url": "https://pf.kakao.com/_hFxaTn/112714189",
  "type": "kakao"
 },
 {
  "handle": "_Fxgrxnn",
  "name": "휴대폰성지 싸당 남양주 다산점",
  "region": "경기도 남양주시",
  "hq": "수도권",
  "url": "https://pf.kakao.com/_Fxgrxnn/112672300",
  "type": "kakao"
 },
 {
  "handle": "_Ctixnn",
  "name": "휴대폰성지 싸당 인천점",
  "region": "인천광역시 부평구",
  "hq": "수도권",
  "url": "https://pf.kakao.com/_Ctixnn/109253238",
  "type": "kakao"
 },
 {
  "handle": "_KWuPG",
  "name": "휴대폰 성지 싸당 동작점",
  "region": "서울특별시 동작구",
  "hq": "수도권",
  "url": "https://pf.kakao.com/_KWuPG/107359094",
  "type": "kakao"
 },
 {
  "handle": "_upfxnxj",
  "name": "휴대폰 성지 싸당 화성점",
  "region": "경기도 화성시",
  "hq": "수도권",
  "url": "https://pf.kakao.com/_upfxnxj/107359130",
  "type": "kakao"
 },
 {
  "handle": "_xcIJXxj",
  "name": "휴대폰 성지 싸당 평택점",
  "region": "경기도 평택시",
  "hq": "수도권",
  "url": "https://pf.kakao.com/_xcIJXxj/107359065",
  "type": "kakao"
 },
 {
  "handle": "_Gpkxmn",
  "name": "휴대폰성지 싸당 군산점",
  "region": "전북 군산시",
  "hq": "서부",
  "url": "https://pf.kakao.com/_Gpkxmn/110715292",
  "type": "kakao"
 },
 {
  "handle": "_xgDiAX",
  "name": "휴대폰 성지 싸당 전주 덕진점",
  "region": "전북 전주시",
  "hq": "서부",
  "url": "https://pf.kakao.com/_xgDiAX/112203919",
  "type": "kakao"
 },
 {
  "handle": "_xcNxaTn",
  "name": "휴대폰성지 싸당 전남 광주 서구점",
  "region": "광주광역시 서구",
  "hq": "서부",
  "url": "https://pf.kakao.com/_xcNxaTn/112588101",
  "type": "kakao"
 },
 {
  "handle": "_LxgBdn",
  "name": "휴대폰성지 싸당 전남광주점",
  "region": "광주광역시 광산구",
  "hq": "서부",
  "url": "https://pf.kakao.com/_LxgBdn/111002660",
  "type": "kakao"
 },
 {
  "handle": "_xcwMFn",
  "name": "휴대폰성지 정직폰",
  "region": "서울특별시 구로구",
  "hq": "수도권",
  "url": "https://pf.kakao.com/_xcwMFn/113049347",
  "type": "kakao"
 },
 {
  "handle": "_mTxoen",
  "name": "휴대폰성지 정직폰 강서점",
  "region": "서울특별시 강서구",
  "hq": "수도권",
  "url": "https://pf.kakao.com/_mTxoen/113048454",
  "type": "kakao"
 },
 {
  "handle": "_xlKexin",
  "name": "휴대폰성지 정직폰 화성점",
  "region": "경기도 화성시",
  "hq": "수도권",
  "url": "https://pf.kakao.com/_xlKexin/113049421",
  "type": "kakao"
 },
 {
  "handle": "_TxbaxhX",
  "name": "휴대폰성지 정직폰 하남점",
  "region": "경기도 하남시",
  "hq": "수도권",
  "url": "https://pf.kakao.com/_TxbaxhX/113004908",
  "type": "kakao"
 },
 {
  "handle": "_MNYIX",
  "name": "휴대폰성지 정직폰 창원점",
  "region": "경상남도 창원시",
  "hq": "부산",
  "url": "https://pf.kakao.com/_MNYIX/113049854",
  "type": "kakao"
 },
 {
  "handle": "_YzxgIX",
  "name": "휴대폰성지 정직폰 김해점",
  "region": "경상남도 김해시",
  "hq": "부산",
  "url": "https://pf.kakao.com/_YzxgIX/113048252",
  "type": "kakao"
 },
 {
  "handle": "_QVMqX",
  "name": "휴대폰성지 정직폰 사상점",
  "region": "부산시 사상구",
  "hq": "부산",
  "url": "https://pf.kakao.com/_QVMqX/113036344",
  "type": "kakao"
 },
 {
  "handle": "_sgzqX",
  "name": "주식회사 더트리플 울산점",
  "region": "울산시 남구",
  "hq": "부산",
  "url": "https://pf.kakao.com/_sgzqX/113048229",
  "type": "kakao"
 },
 {
  "handle": "_xfQpxcn",
  "name": "휴대폰성지 정직폰 전주점",
  "region": "전라북도 전주시",
  "hq": "서부",
  "url": "https://pf.kakao.com/_xfQpxcn/112986987",
  "type": "kakao"
 },
 {
  "handle": "_nxjgYn",
  "name": "휴대폰성지 정직폰 천안점",
  "region": "충청남도 천안시",
  "hq": "중부",
  "url": "https://pf.kakao.com/_nxjgYn/113050665",
  "type": "kakao"
 },
 {
  "handle": "_dGixnxl",
  "name": "휴대폰성지 폰슐랭(온라인 직영점)",
  "region": "전국",
  "hq": "",
  "url": "https://pf.kakao.com/_dGixnxl/109418155",
  "type": "kakao"
 },
 {
  "handle": "_xjbWxaj",
  "name": "폰슐랭샵&엘지티샵_특판",
  "region": "전국",
  "hq": "",
  "url": "https://pf.kakao.com/_xjbWxaj/111325964",
  "type": "kakao"
 },
 {
  "handle": "_xlTXHG",
  "name": "폰슐랭 라이언인형 - 전국택배",
  "region": "전국",
  "hq": "",
  "url": "https://pf.kakao.com/_xlTXHG/105819668",
  "type": "kakao"
 },
 {
  "handle": "_PTPkn",
  "name": "휴대폰성지폰슐랭 성동구지점",
  "region": "서울특별시 성동구",
  "hq": "수도권",
  "url": "https://pf.kakao.com/_PTPkn/110822020",
  "type": "kakao"
 },
 {
  "handle": "_dMCHG",
  "name": "휴대폰성지 폰슐랭 동작구지점",
  "region": "서울특별시 동작구",
  "hq": "수도권",
  "url": "https://pf.kakao.com/_dMCHG/105847535",
  "type": "kakao"
 },
 {
  "handle": "_xakFYn",
  "name": "휴대폰성지 폰슐랭 동대문구점",
  "region": "서울특별시 동대문구",
  "hq": "수도권",
  "url": "https://pf.kakao.com/_xakFYn/111548605",
  "type": "kakao"
 },
 {
  "handle": "_LvxkLG",
  "name": "폰슐랭춘식이인형-금천점",
  "region": "서울특별시 금천구",
  "hq": "수도권",
  "url": "https://pf.kakao.com/_LvxkLG/105864266",
  "type": "kakao"
 },
 {
  "handle": "_UExoJG",
  "name": "휴대폰성지 폰슐랭 구로구지점",
  "region": "서울특별시 구로구",
  "hq": "수도권",
  "url": "https://pf.kakao.com/_UExoJG/105864243",
  "type": "kakao"
 },
 {
  "handle": "_nLxirG",
  "name": "휴대폰성지 폰슐랭 광진구지점",
  "region": "서울특별시 광진구",
  "hq": "수도권",
  "url": "https://pf.kakao.com/_nLxirG/105648838",
  "type": "kakao"
 },
 {
  "handle": "_xeEpFG",
  "name": "휴대폰성지 폰슐랭 관악구지점",
  "region": "서울특별시 관악구",
  "hq": "수도권",
  "url": "https://pf.kakao.com/_xeEpFG/105648849",
  "type": "kakao"
 },
 {
  "handle": "_jxeFNG",
  "name": "휴대폰성지 폰슐랭 강서점",
  "region": "서울특별시 강서구",
  "hq": "수도권",
  "url": "https://pf.kakao.com/_jxeFNG/105864249",
  "type": "kakao"
 },
 {
  "handle": "_jWtqn",
  "name": "폰슐랭 라이언인형 - 화성점",
  "region": "경기도 화성시",
  "hq": "수도권",
  "url": "https://pf.kakao.com/_jWtqn/107782297",
  "type": "kakao"
 },
 {
  "handle": "_niPPn",
  "name": "휴대폰성지 폰슐랭 화성 향남지점",
  "region": "경기도 화성시",
  "hq": "수도권",
  "url": "https://pf.kakao.com/_niPPn/109348134",
  "type": "kakao"
 },
 {
  "handle": "_WxkxhyG",
  "name": "휴대폰성지 폰슐랭 평택지점",
  "region": "경기도 평택시",
  "hq": "수도권",
  "url": "https://pf.kakao.com/_WxkxhyG/106220201",
  "type": "kakao"
 },
 {
  "handle": "_XucUn",
  "name": "휴대폰성지 폰슐랭 파주지점",
  "region": "경기도 파주시",
  "hq": "수도권",
  "url": "https://pf.kakao.com/_XucUn/110911269",
  "type": "kakao"
 },
 {
  "handle": "_KtsIn",
  "name": "휴대폰성지 폰슐랭 의정부지점",
  "region": "경기도 의정부시",
  "hq": "수도권",
  "url": "https://pf.kakao.com/_KtsIn/112945270",
  "type": "kakao"
 },
 {
  "handle": "_llpFG",
  "name": "휴대폰성지 폰슐랭 용인지점",
  "region": "경기도 용인시",
  "hq": "수도권",
  "url": "https://pf.kakao.com/_llpFG/105648853",
  "type": "kakao"
 },
 {
  "handle": "_ywBln",
  "name": "폰슐랭 - 오산점",
  "region": "경기도 오산시",
  "hq": "수도권",
  "url": "https://pf.kakao.com/_ywBln/107289465",
  "type": "kakao"
 },
 {
  "handle": "_yXKxkn",
  "name": "휴대폰성지 폰슐랭 시흥점",
  "region": "경기도 시흥시",
  "hq": "수도권",
  "url": "https://pf.kakao.com/_yXKxkn/111300138",
  "type": "kakao"
 },
 {
  "handle": "_xeimYxj",
  "name": "휴대폰성지 폰슐랭 수원지점",
  "region": "경기도 수원시",
  "hq": "수도권",
  "url": "https://pf.kakao.com/_xeimYxj/105648833",
  "type": "kakao"
 },
 {
  "handle": "_cKldn",
  "name": "휴대폰성지 폰슐랭 성남지점",
  "region": "경기도 성남시",
  "hq": "수도권",
  "url": "https://pf.kakao.com/_cKldn/107749131",
  "type": "kakao"
 },
 {
  "handle": "_xfxjldn",
  "name": "휴대폰성지 폰슐랭 부천지점",
  "region": "경기도 부천시",
  "hq": "수도권",
  "url": "https://pf.kakao.com/_xfxjldn/107889940",
  "type": "kakao"
 },
 {
  "handle": "_SRhKn",
  "name": "휴대폰성지 폰슐랭 남양주지점",
  "region": "경기도 남양주시",
  "hq": "수도권",
  "url": "https://pf.kakao.com/_SRhKn/108246863",
  "type": "kakao"
 },
 {
  "handle": "_xaxfxbGn",
  "name": "휴대폰성지 폰슐랭 고양지점",
  "region": "경기도 고양시",
  "hq": "수도권",
  "url": "https://pf.kakao.com/_xaxfxbGn/109027527",
  "type": "kakao"
 },
 {
  "handle": "_vxixlVn",
  "name": "휴대폰성지 폰슐랭 인천 서구지점",
  "region": "인천시 서구",
  "hq": "수도권",
  "url": "https://pf.kakao.com/_vxixlVn/107505032",
  "type": "kakao"
 },
 {
  "handle": "_ducgG",
  "name": "휴대폰성지 폰슐랭 인천 부평구지점",
  "region": "인천시 부평구",
  "hq": "수도권",
  "url": "https://pf.kakao.com/_ducgG/106488287",
  "type": "kakao"
 },
 {
  "handle": "_xfcMZn",
  "name": "휴대폰성지 폰슐랭 인천 남동구지점",
  "region": "인천시 남동구",
  "hq": "수도권",
  "url": "https://pf.kakao.com/_xfcMZn/107517595",
  "type": "kakao"
 },
 {
  "handle": "_Zrrwn",
  "name": "부산휴대폰성지 폰슐랭(부산 본점)",
  "region": "부산시",
  "hq": "부산",
  "url": "https://pf.kakao.com/_Zrrwn/109050943",
  "type": "kakao"
 },
 {
  "handle": "_xbYxbxdn",
  "name": "휴대폰성지 폰슐랭 부산 수영구지점",
  "region": "부산시 수영구",
  "hq": "부산",
  "url": "https://pf.kakao.com/_xbYxbxdn/110666549",
  "type": "kakao"
 },
 {
  "handle": "_MKIen",
  "name": "휴대폰성지 폰슐랭 부산 사하구지점",
  "region": "부산시 사하구",
  "hq": "부산",
  "url": "https://pf.kakao.com/_MKIen/110538399",
  "type": "kakao"
 },
 {
  "handle": "_xoxjCxbn",
  "name": "휴대폰성지 폰슐랭 부산 북구지점",
  "region": "부산시 북구",
  "hq": "부산",
  "url": "https://pf.kakao.com/_xoxjCxbn/111008695",
  "type": "kakao"
 },
 {
  "handle": "_TxeIQn",
  "name": "휴대폰성지 폰슐랭 부산 동래구지점",
  "region": "부산시 동래구",
  "hq": "부산",
  "url": "https://pf.kakao.com/_TxeIQn/111824275",
  "type": "kakao"
 },
 {
  "handle": "_xgxoxaHn",
  "name": "휴대폰성지 폰슐랭 부산 남구지점",
  "region": "부산시 남구",
  "hq": "부산",
  "url": "https://pf.kakao.com/_xgxoxaHn/111357598",
  "type": "kakao"
 },
 {
  "handle": "_xhjskn",
  "name": "휴대폰성지 폰슐랭 경남 창원지점",
  "region": "경상남도 창원시",
  "hq": "부산",
  "url": "https://pf.kakao.com/_xhjskn/110760186",
  "type": "kakao"
 },
 {
  "handle": "_xixcwPn",
  "name": "휴대폰성지 폰슐랭 경남 양산지점",
  "region": "경상남도 양산시",
  "hq": "부산",
  "url": "https://pf.kakao.com/_xixcwPn/109998976",
  "type": "kakao"
 },
 {
  "handle": "_LKxexnn",
  "name": "휴대폰성지 폰슐랭 대전지점",
  "region": "대전시",
  "hq": "중부",
  "url": "https://pf.kakao.com/_LKxexnn/109294455",
  "type": "kakao"
 },
 {
  "handle": null,
  "name": "옆커폰",
  "region": "네이버 카페",
  "hq": "",
  "url": "https://cafe.naver.com/09tellecom",
  "type": "naver_cafe"
 },
 {
  "handle": "_PuVxmG",
  "name": "옆커폰 신정점",
  "region": "서울특별시 양천구",
  "hq": "수도권",
  "url": "https://pf.kakao.com/_PuVxmG",
  "type": "kakao"
 },
 {
  "handle": null,
  "name": "옆커폰 신방화점",
  "region": "서울특별시 강서구",
  "hq": "수도권",
  "url": "https://naver.me/xNpLMQrv",
  "type": "naver"
 },
 {
  "handle": "_dxiqsn",
  "name": "옆커폰 광흥창역점",
  "region": "서울특별시 마포구",
  "hq": "수도권",
  "url": "https://pf.kakao.com/_dxiqsn",
  "type": "kakao"
 },
 {
  "handle": "_FBHKG",
  "name": "옆커폰 상일점",
  "region": "서울특별시 강동구",
  "hq": "수도권",
  "url": "https://pf.kakao.com/_FBHKG",
  "type": "kakao"
 },
 {
  "handle": "_xfdByxj",
  "name": "옆커폰 청파점",
  "region": "서울특별시 용산구",
  "hq": "수도권",
  "url": "https://pf.kakao.com/_xfdByxj",
  "type": "kakao"
 },
 {
  "handle": "_xnGwrG",
  "name": "옆커폰 신내점",
  "region": "서울특별시 중랑구",
  "hq": "수도권",
  "url": "https://pf.kakao.com/_xnGwrG",
  "type": "kakao"
 },
 {
  "handle": "_bkzNG",
  "name": "옆커폰 강서내발산점",
  "region": "서울특별시 강서구",
  "hq": "수도권",
  "url": "https://pf.kakao.com/_bkzNG",
  "type": "kakao"
 },
 {
  "handle": "_xhCByxj",
  "name": "옆커폰 길음점",
  "region": "서울특별시 성북구",
  "hq": "수도권",
  "url": "https://pf.kakao.com/_xhCByxj",
  "type": "kakao"
 },
 {
  "handle": "_xdxalxnn",
  "name": "옆커폰 불광역점",
  "region": "서울특별시 은평구",
  "hq": "수도권",
  "url": "https://pf.kakao.com/_xdxalxnn",
  "type": "kakao"
 },
 {
  "handle": "_xlxmWxdn",
  "name": "옆커폰 이대역점",
  "region": "서울특별시 마포구",
  "hq": "수도권",
  "url": "https://pf.kakao.com/_xlxmWxdn",
  "type": "kakao"
 },
 {
  "handle": "_eisyxj",
  "name": "휴대폰성지 옆커폰 안양 호계점",
  "region": "경기도 안양시",
  "hq": "수도권",
  "url": "https://pf.kakao.com/_eisyxj",
  "type": "kakao"
 },
 {
  "handle": "_eixiPG",
  "name": "옆커폰 부천 휴대폰 성지",
  "region": "경기도 부천시",
  "hq": "수도권",
  "url": "https://pf.kakao.com/_eixiPG",
  "type": "kakao"
 },
 {
  "handle": "_PuJqG",
  "name": "휴대폰성지 옆커폰 안양점",
  "region": "경기도 안양시",
  "hq": "수도권",
  "url": "https://pf.kakao.com/_PuJqG",
  "type": "kakao"
 },
 {
  "handle": "_xekYxiG",
  "name": "휴대폰성지 옆커폰 수원영통점",
  "region": "경기도 수원시",
  "hq": "수도권",
  "url": "https://pf.kakao.com/_xekYxiG",
  "type": "kakao"
 },
 {
  "handle": "_xcXvQxj",
  "name": "안산휴대폰성지 옆커폰 안산초지점",
  "region": "경기도 안산시",
  "hq": "수도권",
  "url": "https://pf.kakao.com/_xcXvQxj",
  "type": "kakao"
 },
 {
  "handle": "_UQiXG",
  "name": "휴대폰성지 옆커폰 분당 직영점",
  "region": "경기도 성남시",
  "hq": "수도권",
  "url": "https://pf.kakao.com/_UQiXG",
  "type": "kakao"
 },
 {
  "handle": "_tSxiiG",
  "name": "평택휴대폰성지 옆커폰이충점",
  "region": "경기도 평택시",
  "hq": "수도권",
  "url": "https://pf.kakao.com/_tSxiiG",
  "type": "kakao"
 },
 {
  "handle": "_HxiFSn",
  "name": "옆커폰 송내역점",
  "region": "경기도 부천시",
  "hq": "수도권",
  "url": "https://pf.kakao.com/_HxiFSn",
  "type": "kakao"
 },
 {
  "handle": "_xomYUn",
  "name": "휴대폰성지 옆커폰 부천상동점",
  "region": "경기도 부천시",
  "hq": "수도권",
  "url": "https://pf.kakao.com/_xomYUn",
  "type": "kakao"
 },
 {
  "handle": "_xfhZxbxj",
  "name": "휴대폰성지 옆커폰 안산점",
  "region": "경기도 안산시",
  "hq": "수도권",
  "url": "https://pf.kakao.com/_xfhZxbxj",
  "type": "kakao"
 },
 {
  "handle": "_mgMxnxj",
  "name": "휴대폰성지 옆커폰 용인상현점",
  "region": "경기도 용인시",
  "hq": "수도권",
  "url": "https://pf.kakao.com/_mgMxnxj",
  "type": "kakao"
 },
 {
  "handle": "_ziEJn",
  "name": "휴대폰성지 옆커폰 원종직영점",
  "region": "경기도 부천시",
  "hq": "수도권",
  "url": "https://pf.kakao.com/_ziEJn",
  "type": "kakao"
 },
 {
  "handle": "_RxnvxhX",
  "name": "휴대폰성지 옆커폰 목동동점",
  "region": "경기도 파주시",
  "hq": "수도권",
  "url": "https://pf.kakao.com/_RxnvxhX",
  "type": "kakao"
 },
 {
  "handle": "_FvwwG",
  "name": "휴대폰성지 옆커폰 수원 망포점",
  "region": "경기도 수원시",
  "hq": "수도권",
  "url": "https://pf.kakao.com/_FvwwG",
  "type": "kakao"
 },
 {
  "handle": "_xfTaXn",
  "name": "휴대폰성지 옆커폰 시흥은계점",
  "region": "경기도 시흥시",
  "hq": "수도권",
  "url": "https://pf.kakao.com/_xfTaXn",
  "type": "kakao"
 },
 {
  "handle": "_lxeFAX",
  "name": "휴대폰성지 옆커폰 남양주다산지금점",
  "region": "경기도 남양주시",
  "hq": "수도권",
  "url": "https://pf.kakao.com/_lxeFAX",
  "type": "kakao"
 },
 {
  "handle": "_qexgxiG",
  "name": "휴대폰성지 옆커폰 하남점",
  "region": "경기도 하남시",
  "hq": "수도권",
  "url": "https://pf.kakao.com/_qexgxiG",
  "type": "kakao"
 },
 {
  "handle": "_XvwwG",
  "name": "휴대폰성지 옆커폰 화성점",
  "region": "경기도 화성시",
  "hq": "수도권",
  "url": "https://pf.kakao.com/_XvwwG",
  "type": "kakao"
 },
 {
  "handle": "_xixowxbn",
  "name": "인천 휴대폰성지 옆커폰 송도점",
  "region": "인천광역시 연수구",
  "hq": "수도권",
  "url": "https://pf.kakao.com/_xixowxbn",
  "type": "kakao"
 },
 {
  "handle": "_RIqxeG",
  "name": "휴대폰 성지 옆커폰 연수동춘점",
  "region": "인천광역시 연수구",
  "hq": "수도권",
  "url": "https://pf.kakao.com/_RIqxeG",
  "type": "kakao"
 },
 {
  "handle": "_xjxfkxjn",
  "name": "휴대폰성지 옆커폰 계산점",
  "region": "인천광역시 계양구",
  "hq": "수도권",
  "url": "https://pf.kakao.com/_xjxfkxjn",
  "type": "kakao"
 },
 {
  "handle": "_rerWxj",
  "name": "휴대폰성지 옆커폰 청라2호점",
  "region": "인천광역시 서구",
  "hq": "수도권",
  "url": "https://pf.kakao.com/_rerWxj",
  "type": "kakao"
 },
 {
  "handle": "_DRfgxj",
  "name": "옆커폰 인천 부평산곡점",
  "region": "인천광역시 부평구",
  "hq": "수도권",
  "url": "https://pf.kakao.com/_DRfgxj",
  "type": "kakao"
 },
 {
  "handle": "_Fxasyxj",
  "name": "인천 휴대폰성지 옆커폰 부평점",
  "region": "인천광역시 부평구",
  "hq": "수도권",
  "url": "https://pf.kakao.com/_Fxasyxj",
  "type": "kakao"
 },
 {
  "handle": "_BHlYn",
  "name": "휴대폰성지 옆커폰 부산괘법점",
  "region": "부산광역시 사상구",
  "hq": "부산",
  "url": "https://pf.kakao.com/_BHlYn",
  "type": "kakao"
 },
 {
  "handle": "_Gyxgjn",
  "name": "부산 휴대폰성지 옆커폰 명지점",
  "region": "부산광역시 강서구",
  "hq": "부산",
  "url": "https://pf.kakao.com/_Gyxgjn",
  "type": "kakao"
 },
 {
  "handle": "_cxjgtG",
  "name": "옆커폰 천곡점",
  "region": "울산광역시 북구",
  "hq": "부산",
  "url": "https://pf.kakao.com/_cxjgtG",
  "type": "kakao"
 },
 {
  "handle": "_txoySM",
  "name": "양산휴대폰성지 옆커폰 중부점",
  "region": "경상남도 양산시",
  "hq": "부산",
  "url": "https://pf.kakao.com/_txoySM",
  "type": "kakao"
 },
 {
  "handle": "_uddJG",
  "name": "휴대폰성지 옆커폰 두실점",
  "region": "부산광역시 금정구",
  "hq": "부산",
  "url": "https://pf.kakao.com/_uddJG",
  "type": "kakao"
 },
 {
  "handle": "_ZWZxgG",
  "name": "휴대폰성지 옆커폰 매곡점",
  "region": "울산광역시 북구",
  "hq": "부산",
  "url": "https://pf.kakao.com/_ZWZxgG",
  "type": "kakao"
 },
 {
  "handle": null,
  "name": "옆커폰 수성점",
  "region": "대구광역시 수성구",
  "hq": "대구",
  "url": "https://naver.me/xM5jf4eR",
  "type": "naver"
 },
 {
  "handle": "_xdxogpG",
  "name": "옆커폰 대구은행역점",
  "region": "대구광역시 수성구",
  "hq": "대구",
  "url": "https://pf.kakao.com/_xdxogpG",
  "type": "kakao"
 },
 {
  "handle": "_UgUxiG",
  "name": "옆커폰 용산점",
  "region": "대구광역시 달서구",
  "hq": "대구",
  "url": "https://pf.kakao.com/_UgUxiG",
  "type": "kakao"
 },
 {
  "handle": "_xaqQxjT",
  "name": "옆커폰 대구 시지점",
  "region": "대구광역시 수성구",
  "hq": "대구",
  "url": "https://pf.kakao.com/_xaqQxjT",
  "type": "kakao"
 },
 {
  "handle": "_tEkQn",
  "name": "옆커폰 하양역점",
  "region": "대구광역시 경산시",
  "hq": "대구",
  "url": "https://pf.kakao.com/_tEkQn",
  "type": "kakao"
 },
 {
  "handle": "_xehITs",
  "name": "옆커폰 월성점",
  "region": "대구광역시 달서구",
  "hq": "대구",
  "url": "https://pf.kakao.com/_xehITs",
  "type": "kakao"
 },
 {
  "handle": "_pxaZfG",
  "name": "옆커폰 성서이곡점",
  "region": "대구광역시 달서구",
  "hq": "대구",
  "url": "https://pf.kakao.com/_pxaZfG",
  "type": "kakao"
 },
 {
  "handle": "_xmPcxdX",
  "name": "옆커폰 수성1가점",
  "region": "대구광역시 수성구",
  "hq": "대구",
  "url": "https://pf.kakao.com/_xmPcxdX",
  "type": "kakao"
 },
 {
  "handle": "_VxefkG",
  "name": "옆커폰 포항양덕점",
  "region": "포항시 북구",
  "hq": "대구",
  "url": "https://pf.kakao.com/_VxefkG",
  "type": "kakao"
 },
 {
  "handle": "_yxhTjn",
  "name": "옆커폰 복현점",
  "region": "대구광역시 북구",
  "hq": "대구",
  "url": "https://pf.kakao.com/_yxhTjn",
  "type": "kakao"
 },
 {
  "handle": "_lerJxj",
  "name": "옆커폰 범물점",
  "region": "대구광역시 수성구",
  "hq": "대구",
  "url": "https://pf.kakao.com/_lerJxj",
  "type": "kakao"
 },
 {
  "handle": "_xdxnZFG",
  "name": "옆커폰 범어점",
  "region": "대구광역시 수성구",
  "hq": "대구",
  "url": "https://pf.kakao.com/_xdxnZFG",
  "type": "kakao"
 },
 {
  "handle": "_nxkxcJn",
  "name": "옆커폰 진천점",
  "region": "대구광역시 달서구",
  "hq": "대구",
  "url": "https://pf.kakao.com/_nxkxcJn",
  "type": "kakao"
 },
 {
  "handle": "_RAAbG",
  "name": "옆커폰 중산펜타힐즈점",
  "region": "경산시",
  "hq": "대구",
  "url": "https://pf.kakao.com/_RAAbG",
  "type": "kakao"
 },
 {
  "handle": "_xaxlTaG",
  "name": "옆커폰 동천점",
  "region": "대구광역시 북구",
  "hq": "대구",
  "url": "https://pf.kakao.com/_xaxlTaG",
  "type": "kakao"
 },
 {
  "handle": "_zsAMG",
  "name": "옆커폰 대구서구점",
  "region": "대구광역시 서구",
  "hq": "대구",
  "url": "https://pf.kakao.com/_zsAMG",
  "type": "kakao"
 },
 {
  "handle": "_dDxeDn",
  "name": "옆커폰 유천점",
  "region": "대구광역시 달서구",
  "hq": "대구",
  "url": "https://pf.kakao.com/_dDxeDn",
  "type": "kakao"
 },
 {
  "handle": "_gseEn",
  "name": "휴대폰성지 옆커폰 삼화지구점",
  "region": "제주 제주시",
  "hq": "서부",
  "url": "https://pf.kakao.com/_gseEn",
  "type": "kakao"
 },
 {
  "handle": "_VgbAG",
  "name": "휴대폰성지 옆커폰 광주광산구점",
  "region": "광주광역시 광산구",
  "hq": "서부",
  "url": "https://pf.kakao.com/_VgbAG",
  "type": "kakao"
 },
 {
  "handle": "_KMzln",
  "name": "옆커폰 대전봉명점",
  "region": "대전광역시 유성구",
  "hq": "중부",
  "url": "https://pf.kakao.com/_KMzln",
  "type": "kakao"
 },
 {
  "handle": "_Jzgxon",
  "name": "옆커폰 청주분평점",
  "region": "청주시 서원구",
  "hq": "중부",
  "url": "https://pf.kakao.com/_Jzgxon",
  "type": "kakao"
 },
 {
  "handle": null,
  "name": "새마을통신",
  "region": "유투브 채널",
  "hq": "",
  "url": "https://youtu.be/vJ9yl7ROVXc?si=HoHRIU8IWGlxno_6",
  "type": "youtube"
 },
 {
  "handle": null,
  "name": "나는 영업인이다",
  "region": "유투브 채널",
  "hq": "",
  "url": "https://youtu.be/sZwKW-X--Xc?si=jEnwrbyLXmR6Sh8L",
  "type": "youtube"
 },
 {
  "handle": "_iUyAG",
  "name": "스마트폰면세점 잠실새내점",
  "region": "서울특별시 송파구",
  "hq": "수도권",
  "url": "https://pf.kakao.com/_iUyAG",
  "type": "kakao"
 },
 {
  "handle": "_RwBXxb",
  "name": "스마트폰면세점 배곧점",
  "region": "경기도 시흥시",
  "hq": "수도권",
  "url": "https://pf.kakao.com/_RwBXxb",
  "type": "kakao"
 },
 {
  "handle": "_Cicss",
  "name": "스마트폰면세점 은계점",
  "region": "경기도 시흥시",
  "hq": "수도권",
  "url": "https://pf.kakao.com/_Cicss",
  "type": "kakao"
 },
 {
  "handle": "_xnRQLT",
  "name": "스마트폰면세점 송산점",
  "region": "경기도 화성시",
  "hq": "수도권",
  "url": "https://pf.kakao.com/_xnRQLT",
  "type": "kakao"
 },
 {
  "handle": "_xdTxcxdn",
  "name": "스마트폰면세점 비봉점",
  "region": "경기도 화성시",
  "hq": "수도권",
  "url": "https://pf.kakao.com/_xdTxcxdn",
  "type": "kakao"
 },
 {
  "handle": "_Qxbuyn",
  "name": "스마트폰면세점 지제점",
  "region": "경기도 평택시",
  "hq": "수도권",
  "url": "https://pf.kakao.com/_Qxbuyn/112199790",
  "type": "kakao"
 },
 {
  "handle": "_xosTxbn",
  "name": "스마트폰면세점 봉담점",
  "region": "경기도 화성시",
  "hq": "수도권",
  "url": "https://pf.kakao.com/_xosTxbn/113596748",
  "type": "kakao"
 },
 {
  "handle": "_xkNSxen",
  "name": "스마트폰면세점 수원 정자동점",
  "region": "경기도 수원시",
  "hq": "수도권",
  "url": "https://pf.kakao.com/_xkNSxen",
  "type": "kakao"
 },
 {
  "handle": "_xhxixdfG",
  "name": "스마트폰면세점 성포점",
  "region": "경기도 안산시",
  "hq": "수도권",
  "url": "https://pf.kakao.com/_xhxixdfG",
  "type": "kakao"
 },
 {
  "handle": "_xjxfIPn",
  "name": "스마트폰면세점 주안점",
  "region": "인천광역시 미추홀구",
  "hq": "수도권",
  "url": "https://pf.kakao.com/_xjxfIPn",
  "type": "kakao"
 },
 {
  "handle": "_UMgBn",
  "name": "스마트폰면세점 그랑자이",
  "region": "경기도 안산시",
  "hq": "수도권",
  "url": "https://pf.kakao.com/_UMgBn",
  "type": "kakao"
 },
 {
  "handle": "_AxbWYn",
  "name": "스마트폰면세점 검단점",
  "region": "인천광역시 서구",
  "hq": "수도권",
  "url": "https://pf.kakao.com/_AxbWYn",
  "type": "kakao"
 },
 {
  "handle": "_CTxern",
  "name": "스마트폰면세점 오산점",
  "region": "경기도 오산시",
  "hq": "수도권",
  "url": "https://pf.kakao.com/_CTxern",
  "type": "kakao"
 },
 {
  "handle": "_hfBXxb",
  "name": "스마트폰면세점 수원점",
  "region": "경기도 수원시",
  "hq": "수도권",
  "url": "https://pf.kakao.com/_hfBXxb",
  "type": "kakao"
 },
 {
  "handle": "_xbxexanX",
  "name": "스마트폰면세점 세교점",
  "region": "경기도 오산시",
  "hq": "수도권",
  "url": "https://pf.kakao.com/_xbxexanX",
  "type": "kakao"
 },
 {
  "handle": "_xhTdqX",
  "name": "스마트폰면세점 청주점",
  "region": "충북 청주시",
  "hq": "중부",
  "url": "https://pf.kakao.com/_xhTdqX/112864416",
  "type": "kakao"
 },
 {
  "handle": "_xdxfDWG",
  "name": "스마트폰면세점 조은통신",
  "region": "대전광역시 서구",
  "hq": "중부",
  "url": "https://pf.kakao.com/_xdxfDWG/posts",
  "type": "kakao"
 },
 {
  "handle": "_EjPxnG",
  "name": "스마트폰면세점 대전",
  "region": "대전광역시 대덕구",
  "hq": "중부",
  "url": "https://pf.kakao.com/_EjPxnG",
  "type": "kakao"
 },
 {
  "handle": "_YCJvj",
  "name": "스마트폰면세점 대구점",
  "region": "대구광역시 달서구",
  "hq": "대구",
  "url": "https://pf.kakao.com/_YCJvj",
  "type": "kakao"
 },
 {
  "handle": "_xoDvxon",
  "name": "스마트폰면세점 창원점",
  "region": "경남 창원시 성산구",
  "hq": "부산",
  "url": "https://pf.kakao.com/_xoDvxon",
  "type": "kakao"
 },
 {
  "handle": null,
  "name": "스마트폰면세점",
  "region": "유투브 채널",
  "hq": "",
  "url": "https://www.youtube.com/@%EC%8A%A4%EB%A7%88%ED%8A%B8%ED%8F%B0%EB%A9%B4%EC%84%B8%EC%A0%90",
  "type": "youtube"
 },
 {
  "handle": "_nPCIX",
  "name": "휴대폰성지 판다폰 타임스페이스점",
  "region": "인천광역시 연수구",
  "hq": "수도권",
  "url": "https://pf.kakao.com/_nPCIX/112534147",
  "type": "kakao"
 },
 {
  "handle": "_LXqPn",
  "name": "휴대폰성지 판다폰 용현점",
  "region": "인천광역시 미추홀구",
  "hq": "수도권",
  "url": "https://pf.kakao.com/_LXqPn/109116330",
  "type": "kakao"
 },
 {
  "handle": "_HFLan",
  "name": "휴대폰성지판다폰 검단점",
  "region": "인천광역시 서구",
  "hq": "수도권",
  "url": "https://pf.kakao.com/_HFLan/110476500",
  "type": "kakao"
 },
 {
  "handle": "_pLqxgn",
  "name": "휴대폰성지 판다폰 광명점",
  "region": "경기도 광명시",
  "hq": "수도권",
  "url": "https://pf.kakao.com/_pLqxgn/111869418",
  "type": "kakao"
 },
 {
  "handle": "_gxlxnxbn",
  "name": "휴대폰성지 판다폰 작전점",
  "region": "인천광역시 계양구",
  "hq": "수도권",
  "url": "https://pf.kakao.com/_gxlxnxbn",
  "type": "kakao"
 },
 {
  "handle": "_FxiCpn",
  "name": "휴대폰성지 판다폰 옥길점",
  "region": "경기도 부천시",
  "hq": "수도권",
  "url": "https://pf.kakao.com/_FxiCpn",
  "type": "kakao"
 },
 {
  "handle": "_xhxoqxgn",
  "name": "휴대폰성지 판다폰 구월점",
  "region": "인천광역시 남동구",
  "hq": "수도권",
  "url": "https://pf.kakao.com/_xhxoqxgn/111929995",
  "type": "kakao"
 },
 {
  "handle": "_ApIxgn",
  "name": "휴대폰성지 판다폰 송도점",
  "region": "인천광역시 연수구",
  "hq": "수도권",
  "url": "https://pf.kakao.com/_ApIxgn",
  "type": "kakao"
 },
 {
  "handle": "_QXxfxgn",
  "name": "휴대폰성지 판다폰 은계점",
  "region": "경기도 시흥시",
  "hq": "수도권",
  "url": "https://pf.kakao.com/_QXxfxgn",
  "type": "kakao"
 },
 {
  "handle": "_cNxbUn",
  "name": "휴대폰성지 판다폰 만수점",
  "region": "인천광역시 남동구",
  "hq": "수도권",
  "url": "https://pf.kakao.com/_cNxbUn",
  "type": "kakao"
 },
 {
  "handle": "_hExbtn",
  "name": "휴대폰성지 판다폰 청라점",
  "region": "인천광역시 서구",
  "hq": "수도권",
  "url": "https://pf.kakao.com/_hExbtn",
  "type": "kakao"
 },
 {
  "handle": "_Zxixhen",
  "name": "휴대폰성지 판다폰 새솔점",
  "region": "경기도 화성시",
  "hq": "수도권",
  "url": "https://pf.kakao.com/_Zxixhen",
  "type": "kakao"
 },
 {
  "handle": "_lxhpGG",
  "name": "휴대폰성지 판다폰 루원시티점",
  "region": "인천광역시 서구",
  "hq": "수도권",
  "url": "https://pf.kakao.com/_lxhpGG",
  "type": "kakao"
 },
 {
  "handle": "_zirLn",
  "name": "휴대폰성지 판다폰 목감점",
  "region": "경기도 시흥시",
  "hq": "수도권",
  "url": "https://pf.kakao.com/_zirLn",
  "type": "kakao"
 },
 {
  "handle": "_YxoCUn",
  "name": "휴대폰성지 판다포노 주안역점",
  "region": "인천광역시 미추홀구",
  "hq": "수도권",
  "url": "https://pf.kakao.com/_YxoCUn",
  "type": "kakao"
 },
 {
  "handle": "_anxomn",
  "name": "휴대폰성지 판다폰",
  "region": "부산광역시 부산진구",
  "hq": "부산",
  "url": "https://pf.kakao.com/_anxomn",
  "type": "kakao"
 },
 {
  "handle": "_xbNUcG",
  "name": "휴대폰성지 판다폰 연제점",
  "region": "부산광역시 연제구",
  "hq": "부산",
  "url": "https://pf.kakao.com/_xbNUcG/110535632",
  "type": "kakao"
 },
 {
  "handle": "_JIfxin",
  "name": "휴대폰성지 판다폰 중동점",
  "region": "경남 창원시 의창구",
  "hq": "부산",
  "url": "https://pf.kakao.com/_JIfxin/110105698",
  "type": "kakao"
 },
 {
  "handle": "_Mynvn",
  "name": "휴대폰성지 판다폰 대안점",
  "region": "경남 진주시",
  "hq": "부산",
  "url": "https://pf.kakao.com/_Mynvn/111825315",
  "type": "kakao"
 },
 {
  "handle": "_FxjMxgn",
  "name": "휴대폰성지 판다폰 장산점",
  "region": "부산시 해운대구",
  "hq": "부산",
  "url": "https://pf.kakao.com/_FxjMxgn/112078883",
  "type": "kakao"
 },
 {
  "handle": "_mpRsX",
  "name": "휴대폰 성지 판다폰 산호점",
  "region": "경남 창원시",
  "hq": "부산",
  "url": "https://pf.kakao.com/_mpRsX",
  "type": "kakao"
 },
 {
  "handle": "_ztIUn",
  "name": "휴대폰성지 판다폰 서산점",
  "region": "충남 서산시",
  "hq": "중부",
  "url": "https://pf.kakao.com/_ztIUn",
  "type": "kakao"
 },
 {
  "handle": "_xjrubn",
  "name": "청주성지 판다폰",
  "region": "충북 청주시",
  "hq": "중부",
  "url": "https://pf.kakao.com/_xjrubn/111206720",
  "type": "kakao"
 },
 {
  "handle": "_fnQWs",
  "name": "대구 휴대폰 파는 총각",
  "region": "",
  "hq": "대구",
  "url": "https://pf.kakao.com/_fnQWs/112517173",
  "type": "kakao"
 },
 {
  "handle": "_JWJSxj",
  "name": "휴대폰파는 총각 중산점",
  "region": "경북 경산시",
  "hq": "대구",
  "url": "https://pf.kakao.com/_JWJSxj",
  "type": "kakao"
 },
 {
  "handle": "_pxdxaFn",
  "name": "휴대폰파는 총각 율하점",
  "region": "대구광역시 동구",
  "hq": "대구",
  "url": "https://pf.kakao.com/_pxdxaFn",
  "type": "kakao"
 },
 {
  "handle": "_wGntxj",
  "name": "휴대폰파는 총각 이곡점",
  "region": "대구광역시 달서구",
  "hq": "대구",
  "url": "https://pf.kakao.com/_wGntxj",
  "type": "kakao"
 },
 {
  "handle": "_dWJSxj",
  "name": "휴대폰파는 총각 만촌점",
  "region": "대구광역시 수성구",
  "hq": "대구",
  "url": "https://pf.kakao.com/_dWJSxj",
  "type": "kakao"
 },
 {
  "handle": "_xfsxixln",
  "name": "휴대폰파는 총각 칠곡3지구점",
  "region": "대구광역시 북구",
  "hq": "대구",
  "url": "https://pf.kakao.com/_xfsxixln",
  "type": "kakao"
 },
 {
  "handle": "_HxbEcG",
  "name": "휴대폰파는 총각 사동점",
  "region": "경북 경산시",
  "hq": "대구",
  "url": "https://pf.kakao.com/_HxbEcG",
  "type": "kakao"
 },
 {
  "handle": "_RxhxgDn",
  "name": "휴대폰파는 총각 성당점",
  "region": "대구광역시 달서구",
  "hq": "대구",
  "url": "https://pf.kakao.com/_RxhxgDn",
  "type": "kakao"
 },
 {
  "handle": "_jxnwzK",
  "name": "국밥폰",
  "region": "서울, 경기, 인천, 경남",
  "hq": "수도권",
  "url": "https://pf.kakao.com/_jxnwzK/107975733",
  "type": "kakao"
 },
 {
  "handle": "_TxaxdDG",
  "name": "강변 호랑이",
  "region": "서울특별시 광진구",
  "hq": "수도권",
  "url": "https://pf.kakao.com/_TxaxdDG/113638333",
  "type": "kakao"
 },
 {
  "handle": "_htFtxb",
  "name": "휴대폰성지 설탕텔레콤 부산대 본점",
  "region": "부산광역시 금정구",
  "hq": "부산",
  "url": "https://pf.kakao.com/_htFtxb/113558171",
  "type": "kakao"
 },
 {
  "handle": "_xdAxgxhxb",
  "name": "휴대폰성지 마징가텔레콤",
  "region": "부산광역시 금정구",
  "hq": "부산",
  "url": "https://pf.kakao.com/_xdAxgxhxb/108409085",
  "type": "kakao"
 },
 {
  "handle": "_xgEdku",
  "name": "스마트핫스팟",
  "region": "",
  "hq": "서부",
  "url": "https://pf.kakao.com/_xgEdku/108395075",
  "type": "kakao"
 },
 {
  "handle": "_xfPgXu",
  "name": "성지폰",
  "region": "",
  "hq": "수도권",
  "url": "https://pf.kakao.com/_xfPgXu/108409190",
  "type": "kakao"
 },
 {
  "handle": "_DIAExb",
  "name": "폰인싸 고객센터",
  "region": "전라북도 익산시",
  "hq": "수도권",
  "url": "https://pf.kakao.com/_DIAExb/104672746",
  "type": "kakao"
 },
 {
  "handle": "_mzIqX",
  "name": "휴대폰성지 띵동폰",
  "region": "서울특별시 광진/마포/은평/중랑",
  "hq": "수도권",
  "url": "https://pf.kakao.com/_mzIqX/113638443",
  "type": "kakao"
 },
 {
  "handle": "_jyQHn",
  "name": "휴대폰성지 최싸폰 동탄점",
  "region": "경기도 화성시",
  "hq": "수도권",
  "url": "https://pf.kakao.com/_jyQHn/111743279",
  "type": "kakao"
 },
 {
  "handle": "_xmxixjpn",
  "name": "휴대폰성지 최싸폰 초지점",
  "region": "경기도 안산시",
  "hq": "수도권",
  "url": "https://pf.kakao.com/_xmxixjpn/113590285",
  "type": "kakao"
 },
 {
  "handle": "_Axlxlcn",
  "name": "휴대폰성지 최싸폰 모라점",
  "region": "부산광역시 사상구",
  "hq": "부산",
  "url": "https://pf.kakao.com/_Axlxlcn/112969180",
  "type": "kakao"
 },
 {
  "handle": "_iQxoxin",
  "name": "휴대폰성지 최싸폰 사송점",
  "region": "경남 양산시",
  "hq": "부산",
  "url": "https://pf.kakao.com/_iQxoxin/110342469",
  "type": "kakao"
 },
 {
  "handle": "_pbwan",
  "name": "휴대폰성지 최싸폰 하양점",
  "region": "경북 경산시",
  "hq": "부산",
  "url": "https://pf.kakao.com/_pbwan/111896544",
  "type": "kakao"
 },
 {
  "handle": "_xhjwxin",
  "name": "휴대폰성지 최싸폰 신대점",
  "region": "경북 경산시",
  "hq": "부산",
  "url": "https://pf.kakao.com/_xhjwxin/110000882",
  "type": "kakao"
 },
 {
  "handle": "_XeqXn",
  "name": "휴대폰성지 최싸폰 남산점",
  "region": "대구광역시 중구",
  "hq": "대구",
  "url": "https://pf.kakao.com/_XeqXn/113155593",
  "type": "kakao"
 },
 {
  "handle": "_KBuvn",
  "name": "휴대폰성지 최싸폰 매호점",
  "region": "대구광역시 수성구",
  "hq": "대구",
  "url": "https://pf.kakao.com/_KBuvn/111744033",
  "type": "kakao"
 },
 {
  "handle": "_xcXxfzX",
  "name": "휴대폰성지 최싸폰 충주점",
  "region": "충북 충주시",
  "hq": "중부",
  "url": "https://pf.kakao.com/_xcXxfzX/113369252",
  "type": "kakao"
 },
 {
  "handle": "_FzSxln",
  "name": "휴대폰성지(믿음)",
  "region": "서울특별시 구로구",
  "hq": "수도권",
  "url": "https://pf.kakao.com/_FzSxln/112246558",
  "type": "kakao"
 },
 {
  "handle": "_VctSG",
  "name": "메가폰성지모바일",
  "region": "서울특별시 동작구",
  "hq": "수도권",
  "url": "https://pf.kakao.com/_VctSG/110614743",
  "type": "kakao"
 },
 {
  "handle": "_xfuHMn",
  "name": "휴대폰성지 갓생폰",
  "region": "광주광역시 광산구",
  "hq": "서부",
  "url": "https://pf.kakao.com/_xfuHMn/111867527",
  "type": "kakao"
 },
 {
  "handle": "_SGxmxcn",
  "name": "원주뽐뿌 휴대폰성지 밴드폰 반곡점",
  "region": "강원도 원주시",
  "hq": "중부",
  "url": "https://pf.kakao.com/_SGxmxcn/110971407",
  "type": "kakao"
 },
 {
  "handle": "_cxhtJn",
  "name": "밴드폰 구리시점",
  "region": "경기도 구리시",
  "hq": "수도권",
  "url": "https://pf.kakao.com/_cxhtJn/109663813",
  "type": "kakao"
 },
 {
  "handle": "_EEtJn",
  "name": "밴드폰 신도림테크노점",
  "region": "서울특별시 구로구",
  "hq": "수도권",
  "url": "https://pf.kakao.com/_EEtJn/109664269",
  "type": "kakao"
 },
 {
  "handle": "_nqtJn",
  "name": "밴드폰 중랑구점",
  "region": "서울특별시 중랑구",
  "hq": "수도권",
  "url": "https://pf.kakao.com/_nqtJn/109653864",
  "type": "kakao"
 },
 {
  "handle": "_AZtJn",
  "name": "밴드폰 고양시점",
  "region": "경기도 고양시",
  "hq": "수도권",
  "url": "https://pf.kakao.com/_AZtJn/109663625",
  "type": "kakao"
 },
 {
  "handle": "_xdqtJn",
  "name": "밴드폰 서초구점",
  "region": "서울특별시 서초구",
  "hq": "수도권",
  "url": "https://pf.kakao.com/_xdqtJn/109663978",
  "type": "kakao"
 },
 {
  "handle": "_pItJn",
  "name": "밴드폰 은평구점",
  "region": "서울특별시 은평구",
  "hq": "수도권",
  "url": "https://pf.kakao.com/_pItJn/posts",
  "type": "kakao"
 },
 {
  "handle": "_kqtJn",
  "name": "밴드폰 강변테크노점",
  "region": "서울특별시 광진구",
  "hq": "수도권",
  "url": "https://pf.kakao.com/_kqtJn/109653851",
  "type": "kakao"
 },
 {
  "handle": "_aZtJn",
  "name": "밴드폰 안산시점",
  "region": "경기도 안산시",
  "hq": "수도권",
  "url": "https://pf.kakao.com/_aZtJn/109664418",
  "type": "kakao"
 },
 {
  "handle": "_aIvrn",
  "name": "밴드폰 용인시점",
  "region": "경기도 용인시",
  "hq": "수도권",
  "url": "https://pf.kakao.com/_aIvrn/109728616",
  "type": "kakao"
 },
 {
  "handle": "_NEDxcn",
  "name": "밴드폰 평택점",
  "region": "경기도 평택시",
  "hq": "수도권",
  "url": "https://pf.kakao.com/_NEDxcn/110971623",
  "type": "kakao"
 },
 {
  "handle": "_xexmeRn",
  "name": "당진밴드폰",
  "region": "충청남도 당진시",
  "hq": "중부",
  "url": "https://pf.kakao.com/_xexmeRn/107775923",
  "type": "kakao"
 },
 {
  "handle": "_cHxiBn",
  "name": "휴대폰성지 폰키호테 강남점",
  "region": "서울특별시 강남구",
  "hq": "수도권",
  "url": "https://pf.kakao.com/_cHxiBn/109473140",
  "type": "kakao"
 },
 {
  "handle": "_BHxiBn",
  "name": "휴대폰성지 폰키호테 성북점",
  "region": "서울특별시 성북구",
  "hq": "수도권",
  "url": "https://pf.kakao.com/_BHxiBn/posts",
  "type": "kakao"
 },
 {
  "handle": "_Hrtvn",
  "name": "휴대폰성지 폰키호테 용산점",
  "region": "서울특별시 용산구",
  "hq": "수도권",
  "url": "https://pf.kakao.com/_Hrtvn/110459919",
  "type": "kakao"
 },
 {
  "handle": "_xixmxccn",
  "name": "휴대폰성지 폰키호테 방학점",
  "region": "서울특별시 도봉구",
  "hq": "수도권",
  "url": "https://pf.kakao.com/_xixmxccn/111297026",
  "type": "kakao"
 },
 {
  "handle": "_ZxechX",
  "name": "휴대폰성지 폰키호테 광명점",
  "region": "경기도 광명시",
  "hq": "수도권",
  "url": "https://pf.kakao.com/_ZxechX/112739884",
  "type": "kakao"
 },
 {
  "handle": "_WlXCX",
  "name": "휴대폰성지 폰키호테 은평점",
  "region": "서울특별시 은평구",
  "hq": "수도권",
  "url": "https://pf.kakao.com/_WlXCX/113252896",
  "type": "kakao"
 },
 {
  "handle": "_xjkQhX",
  "name": "휴대폰성지 폰키호테 인천서구점",
  "region": "인천광역시 서구",
  "hq": "수도권",
  "url": "https://pf.kakao.com/_xjkQhX/112425089",
  "type": "kakao"
 },
 {
  "handle": "_dxcxnhG",
  "name": "땡폰",
  "region": "세종특별자치시",
  "hq": "중부",
  "url": "https://pf.kakao.com/_dxcxnhG/109798943",
  "type": "kakao"
 },
 {
  "handle": "_xexldxbX",
  "name": "휴대폰성지 에스디모바일",
  "region": "부산광역시 해운대구",
  "hq": "부산",
  "url": "https://pf.kakao.com/_xexldxbX/113279925",
  "type": "kakao"
 },
 {
  "handle": "_Wxexexin",
  "name": "마징가텔레콤 해운대 장산점",
  "region": "부산광역시 해운대구",
  "hq": "부산",
  "url": "https://pf.kakao.com/_Wxexexin/109891848",
  "type": "kakao"
 },
 {
  "handle": "_HxmExcn",
  "name": "휴대폰성지 올영폰 칠성점",
  "region": "대구광역시 북구",
  "hq": "대구",
  "url": "https://pf.kakao.com/_HxmExcn/110991172",
  "type": "kakao"
 },
 {
  "handle": "_xdSxdLb",
  "name": "휴대폰성지 올영폰 구미산동점",
  "region": "경상북도 구미시",
  "hq": "대구",
  "url": "https://pf.kakao.com/_xdSxdLb/111257117",
  "type": "kakao"
 },
 {
  "handle": "_nxgvxhX",
  "name": "휴대폰성지 올영폰 구미진평점",
  "region": "경상북도 구미시",
  "hq": "대구",
  "url": "https://pf.kakao.com/_nxgvxhX/112798343",
  "type": "kakao"
 },
 {
  "handle": "_FCxkxnxj",
  "name": "휴대폰상담원",
  "region": "대구광역시 달서구",
  "hq": "대구",
  "url": "https://pf.kakao.com/_FCxkxnxj/107334969",
  "type": "kakao"
 },
 {
  "handle": "_wMRKX",
  "name": "휴대폰성지 선통신 고양점",
  "region": "경기도 고양시",
  "hq": "수도권",
  "url": "https://pf.kakao.com/_wMRKX/113568728",
  "type": "kakao"
 },
 {
  "handle": "_QWMYn",
  "name": "휴대폰성지 선통신 양천본점",
  "region": "서울특별시 양천구",
  "hq": "수도권",
  "url": "https://pf.kakao.com/_QWMYn/113156550",
  "type": "kakao"
 },
 {
  "handle": "_xhxlTGn",
  "name": "노원구 성지",
  "region": "서울특별시 노원구",
  "hq": "수도권",
  "url": "https://pf.kakao.com/_xhxlTGn/108588929",
  "type": "kakao"
 },
 {
  "handle": "_aWqQn",
  "name": "2호선 테크노마트 성지",
  "region": "서울특별시 구로구",
  "hq": "수도권",
  "url": "https://pf.kakao.com/_aWqQn/111826532",
  "type": "kakao"
 },
 {
  "handle": "_jJwqX",
  "name": "대구휴대폰성지 이음모바일",
  "region": "대구광역시 달서구",
  "hq": "대구",
  "url": "https://pf.kakao.com/_jJwqX/112623700",
  "type": "kakao"
 },
 {
  "handle": "_nxggxkb",
  "name": "충청도남바완통신",
  "region": "대전광역시 유성구",
  "hq": "중부",
  "url": "https://pf.kakao.com/_nxggxkb/109462383",
  "type": "kakao"
 },
 {
  "handle": "_fMPxkK",
  "name": "구미휴대폰성지(문성점)",
  "region": "경상북도 구미시",
  "hq": "대구",
  "url": "https://pf.kakao.com/_fMPxkK/112353125",
  "type": "kakao"
 },
 {
  "handle": "_xkhxaUb",
  "name": "구미휴대폰성지(황상점)",
  "region": "경상북도 구미시",
  "hq": "대구",
  "url": "https://pf.kakao.com/_xkhxaUb/112440595",
  "type": "kakao"
 },
 {
  "handle": "_ghfhn",
  "name": "휴대폰성지 퍼스트폰",
  "region": "경상북도 구미시",
  "hq": "대구",
  "url": "https://pf.kakao.com/_ghfhn/106524117",
  "type": "kakao"
 },
 {
  "handle": "_cfgWxj",
  "name": "파주 휴대폰성지",
  "region": "경기도 파주시",
  "hq": "수도권",
  "url": "https://pf.kakao.com/_cfgWxj/109424985",
  "type": "kakao"
 },
 {
  "handle": "_Wquqxb",
  "name": "휴대폰성지 우동폰 부천점",
  "region": "경기도 부천시",
  "hq": "수도권",
  "url": "https://pf.kakao.com/_Wquqxb/106229519",
  "type": "kakao"
 },
 {
  "handle": "_xeMCxcG",
  "name": "휴대폰성지 청년폰 안양점",
  "region": "경기도 안양시",
  "hq": "수도권",
  "url": "https://pf.kakao.com/_xeMCxcG/113523696",
  "type": "kakao"
 },
 {
  "handle": "_xfkxaxoG",
  "name": "휴대폰성지 청년폰 용산점",
  "region": "서울특별시 용산구",
  "hq": "수도권",
  "url": "https://pf.kakao.com/_xfkxaxoG/113638702",
  "type": "kakao"
 },
 {
  "handle": "_cxdmxcn",
  "name": "휴대폰성지 청년폰 하남미사점",
  "region": "경기도 하남시",
  "hq": "수도권",
  "url": "https://pf.kakao.com/_cxdmxcn/113638657",
  "type": "kakao"
 },
 {
  "handle": "_xmxdCxcG",
  "name": "휴대폰성지 청년폰 신도림테크노마트점",
  "region": "서울특별시 구로구",
  "hq": "수도권",
  "url": "https://pf.kakao.com/_xmxdCxcG/113456529",
  "type": "kakao"
 },
 {
  "handle": "_TuQYn",
  "name": "휴대폰성지 청년폰 의정부점",
  "region": "경기도 의정부시",
  "hq": "수도권",
  "url": "https://pf.kakao.com/_TuQYn/112569664",
  "type": "kakao"
 },
 {
  "handle": "_xlVDAG",
  "name": "휴대폰성지 청년폰 송파점",
  "region": "서울특별시 송파구",
  "hq": "수도권",
  "url": "https://pf.kakao.com/_xlVDAG/113523671",
  "type": "kakao"
 },
 {
  "handle": "_fxgbMn",
  "name": "휴대폰성지 청년폰 강북점",
  "region": "서울특별시 도봉구",
  "hq": "수도권",
  "url": "https://pf.kakao.com/_fxgbMn/113523606",
  "type": "kakao"
 },
 {
  "handle": "_xbPfPn",
  "name": "휴대폰성지 부천점",
  "region": "경기도 부천시",
  "hq": "수도권",
  "url": "https://pf.kakao.com/_xbPfPn/111754916",
  "type": "kakao"
 },
 {
  "handle": "_tNPPn",
  "name": "휴대폰성지 서울지점",
  "region": "서울특별시 구로구",
  "hq": "수도권",
  "url": "https://pf.kakao.com/_tNPPn/112558774",
  "type": "kakao"
 },
 {
  "handle": "_cxemZn",
  "name": "휴대폰성지 핫딜폰 인천 구월점",
  "region": "인천광역시 남동구",
  "hq": "수도권",
  "url": "https://pf.kakao.com/_cxemZn/109726360",
  "type": "kakao"
 },
 {
  "handle": "_yTzRX",
  "name": "휴대폰성지 핫딜폰 인천 검단점",
  "region": "인천광역시 서구",
  "hq": "수도권",
  "url": "https://pf.kakao.com/_yTzRX/112406526",
  "type": "kakao"
 },
 {
  "handle": "_xkEvzn",
  "name": "휴대폰365아울렛",
  "region": "경상북도 경산시",
  "hq": "대구",
  "url": "https://pf.kakao.com/_xkEvzn/110755449",
  "type": "kakao"
 },
 {
  "handle": "_Dxewxfn",
  "name": "휴대폰365아울렛 경산점",
  "region": "경상북도 경산시",
  "hq": "대구",
  "url": "https://pf.kakao.com/_Dxewxfn/109186564",
  "type": "kakao"
 },
 {
  "handle": "_RpVSn",
  "name": "휴대폰365아울렛",
  "region": "전라남도 순천시",
  "hq": "서부",
  "url": "https://pf.kakao.com/_RpVSn/111809739",
  "type": "kakao"
 },
 {
  "handle": "_xhQXPn",
  "name": "휴대폰성지 인천점",
  "region": "인천광역시 서구",
  "hq": "수도권",
  "url": "https://pf.kakao.com/_xhQXPn/113627849",
  "type": "kakao"
 },
 {
  "handle": "_xaxnJLn",
  "name": "휴대폰성지 김포점",
  "region": "경기도 김포시",
  "hq": "수도권",
  "url": "https://pf.kakao.com/_xaxnJLn/113627883",
  "type": "kakao"
 },
 {
  "handle": "_xdBZPG",
  "name": "휴대폰성지 토르모바일 천호역점",
  "region": "서울특별시 강동구",
  "hq": "수도권",
  "url": "https://pf.kakao.com/_xdBZPG/103855552",
  "type": "kakao"
 },
 {
  "handle": "_xnxfRxkj",
  "name": "휴대폰성지 토르모바일 신도림점",
  "region": "서울특별시 구로구",
  "hq": "수도권",
  "url": "https://pf.kakao.com/_xnxfRxkj/107457831",
  "type": "kakao"
 },
 {
  "handle": "_DRUYb",
  "name": "휴대폰성지 토르모바일 강변점",
  "region": "서울특별시 광진구",
  "hq": "수도권",
  "url": "https://pf.kakao.com/_DRUYb/107457805",
  "type": "kakao"
 },
 {
  "handle": "_WjeXn",
  "name": "휴대폰성지 테크노마트 토르",
  "region": "서울특별시 광진구",
  "hq": "수도권",
  "url": "https://pf.kakao.com/_WjeXn/110460379",
  "type": "kakao"
 },
 {
  "handle": "_svyAs",
  "name": "휴대폰성지 토르모바일 부평점",
  "region": "인천광역시 부평구",
  "hq": "수도권",
  "url": "https://pf.kakao.com/_svyAs/112874130",
  "type": "kakao"
 },
 {
  "handle": "_PuxeHn",
  "name": "휴대폰성지 토르모바일 하남미사점",
  "region": "경기도 하남시",
  "hq": "수도권",
  "url": "https://pf.kakao.com/_PuxeHn/111367820",
  "type": "kakao"
 },
 {
  "handle": "_aRMdX",
  "name": "휴대폰아울렛 항동점",
  "region": "서울특별시 구로구",
  "hq": "수도권",
  "url": "https://pf.kakao.com/_aRMdX/113639017",
  "type": "kakao"
 },
 {
  "handle": "_UxkUgxb",
  "name": "휴대폰아울렛",
  "region": "부산광역시 동래구",
  "hq": "부산",
  "url": "https://pf.kakao.com/_UxkUgxb/108768605",
  "type": "kakao"
 },
 {
  "handle": "_jCxbzX",
  "name": "휴대폰성지 폰킹 신월점",
  "region": "서울특별시 양천구",
  "hq": "수도권",
  "url": "https://pf.kakao.com/_jCxbzX/112610733",
  "type": "kakao"
 },
 {
  "handle": "_bWwzX",
  "name": "휴대폰성지 폰킹",
  "region": "인천광역시 서구",
  "hq": "수도권",
  "url": "https://pf.kakao.com/_bWwzX/112754514",
  "type": "kakao"
 },
 {
  "handle": "_xcxjxaIX",
  "name": "휴대폰성지 폰킹 검단점",
  "region": "인천광역시 서구",
  "hq": "수도권",
  "url": "https://pf.kakao.com/_xcxjxaIX/112653932",
  "type": "kakao"
 },
 {
  "handle": "_zxfxkxhX",
  "name": "휴대폰성지 폰킹 지축점",
  "region": "경기도 고양시",
  "hq": "수도권",
  "url": "https://pf.kakao.com/_zxfxkxhX/112834215",
  "type": "kakao"
 }
]